por_extenso/__init__.py
por_extenso/funcoes.py
por_extenso-0.0.1.dist-info/LICENSE
por_extenso-0.0.1.dist-info/METADATA
por_extenso-0.0.1.dist-info/WHEEL
por_extenso-0.0.1.dist-info/top_level.txt
por_extenso-0.0.1.dist-info/RECORD
