Metadata-Version: 2.1
Name: por_extenso
Version: 0.0.1
Summary: Transforma algarismos em texto por extenso, observando as regras gramaticais
Author-email: Rafael Leite <rafxel@gmail.com>
Project-URL: Homepage, https://github.com/rafxel/por_extenso
Project-URL: Bug Tracker, https://github.com/rafxel/por_extenso/issues
Classifier: Programming Language :: Python :: 3
Classifier: License :: OSI Approved :: MIT License
Classifier: Operating System :: OS Independent
Requires-Python: >=3.7
License-File: LICENSE
